mythx_models/__init__.py
mythx_models/exceptions.py
mythx_models/request/__init__.py
mythx_models/request/analysis_input.py
mythx_models/request/analysis_list.py
mythx_models/request/analysis_status.py
mythx_models/request/analysis_submission.py
mythx_models/request/auth_login.py
mythx_models/request/auth_logout.py
mythx_models/request/auth_refresh.py
mythx_models/request/detected_issues.py
mythx_models/request/group_creation.py
mythx_models/request/group_list.py
mythx_models/request/group_operation.py
mythx_models/request/group_status.py
mythx_models/request/project_creation.py
mythx_models/request/project_deletion.py
mythx_models/request/project_list.py
mythx_models/request/project_status.py
mythx_models/request/project_update.py
mythx_models/request/version.py
mythx_models/response/__init__.py
mythx_models/response/analysis.py
mythx_models/response/analysis_input.py
mythx_models/response/analysis_list.py
mythx_models/response/analysis_status.py
mythx_models/response/analysis_submission.py
mythx_models/response/auth_login.py
mythx_models/response/auth_logout.py
mythx_models/response/auth_refresh.py
mythx_models/response/detected_issues.py
mythx_models/response/group.py
mythx_models/response/group_creation.py
mythx_models/response/group_list.py
mythx_models/response/group_operation.py
mythx_models/response/group_status.py
mythx_models/response/issue.py
mythx_models/response/project.py
mythx_models/response/project_creation.py
mythx_models/response/project_deletion.py
mythx_models/response/project_list.py
mythx_models/response/project_status.py
mythx_models/response/project_update.py
mythx_models/response/version.py
mythx_models/util.py
mythx_models-3.0.0.dist-info/AUTHORS.rst
mythx_models-3.0.0.dist-info/METADATA
mythx_models-3.0.0.dist-info/WHEEL
mythx_models-3.0.0.dist-info/RECORD
