Metadata-Version: 2.1
Name: mythx-models
Version: 3.0.0
Summary: Python domain model classes for the MythX platform
Home-page: https://github.com/Consensys/mythx-models
License: MIT
Author: Dominik Muhs
Author-email: dominik.muhs@consensys.net
Maintainer: Nuradil Alymkulov
Maintainer-email: nuradil.alymkulov-ext@consensys.net
Requires-Python: >=3.8,<4
Classifier: License :: OSI Approved :: MIT License
Classifier: Programming Language :: Python :: 3
Classifier: Programming Language :: Python :: 3.8
Classifier: Programming Language :: Python :: 3.9
Classifier: Programming Language :: Python :: 3.10
Classifier: Programming Language :: Python :: 3.11
Classifier: Programming Language :: Python :: 3.12
Requires-Dist: pydantic (>=2.6.3)
Requires-Dist: python-dateutil (==2.*)
